xgbimputer/__init__.py
xgbimputer/utils.py
xgbimputer/xgbimputer.py
xgbimputer-0.2.0.dist-info/LICENSE.md
xgbimputer-0.2.0.dist-info/METADATA
xgbimputer-0.2.0.dist-info/WHEEL
xgbimputer-0.2.0.dist-info/top_level.txt
xgbimputer-0.2.0.dist-info/RECORD
