Metadata-Version: 2.1
Name: xgbimputer
Version: 0.2.0
Summary: Extreme Gradient Boosting imputer for Machine Learning.
Home-page: https://github.com/leonardodepaula/xgbimputer
Author: Leonardo de Paula Liebscher
Author-email: <leonardopx@gmail.com>
License: UNKNOWN
Keywords: python,machine learning,missing values,imputation
Platform: UNKNOWN
Classifier: Intended Audience :: Science/Research
Classifier: License :: OSI Approved :: Apache Software License
Classifier: Programming Language :: Python
Classifier: Development Status :: 4 - Beta
License-File: LICENSE.md
Requires-Dist: numpy (>=1.21)
Requires-Dist: scikit-learn (>=1.0)
Requires-Dist: xgboost (>=1.5)
